{
  "kind": "collectionType",
  "collectionName": "orders",
  "info": {
    "singularName": "order",
    "pluralName": "orders",
    "displayName": "Ordenes",
    "description": "Customer orders and payment information"
  },
  "options": {
    "draftAndPublish": false
  },
  "pluginOptions": {},
  "attributes": {
    "external_reference": {
      "type": "string",
      "required": true,
      "unique": true
    },
    "payment_id": {
      "type": "string"
    },
    "payment_status": {
      "type": "enumeration",
      "required": true,
      "default": "pending",
      "enum": [
        "pending",
        "approved",
        "rejected",
        "refunded",
        "cancelled",
        "in_process",
        "in_mediation",
        "charged_back"
      ]
    },
    "payment_method": {
      "type": "string"
    },
    "payment_type": {
      "type": "string"
    },
    "transaction_amount": {
      "type": "decimal"
    },
    "customer_email": {
      "type": "email"
    },
    "customer_name": {
      "type": "string"
    },
    "customer_phone": {
      "type": "string"
    },
    "customer_dni": {
      "type": "string"
    },
    "customer_document_type": {
      "type": "enumeration",
      "required": true,
      "default": "DNI",
      "enum": [
        "DNI",
        "CUIT"
      ]
    },
    "customer_fiscal_category": {
      "type": "enumeration",
      "required": true,
      "default": "CONSUMIDOR_FINAL",
      "enum": [
        "CONSUMIDOR_FINAL",
        "RESPONSABLE_INSCRIPTO",
        "EXENTO",
        "MONOTRIBUTISTA"
      ]
    },
    "customer_address": {
      "type": "text"
    },
    "items": {
      "type": "json",
      "required": true
    },
    "metadata": {
      "type": "json"
    },
    "webhook_notifications": {
      "type": "json"
    },
    "mercadopago_data": {
      "type": "json"
    },
    "dux_invoice_id": {
      "type": "string"
    },
    "dux_invoice_number": {
      "type": "string"
    },
    "dux_invoice_status": {
      "type": "enumeration",
      "default": "pending",
      "enum": [
        "pending",
        "created",
        "failed",
        "retrying"
      ]
    },
    "dux_invoice_data": {
      "type": "json"
    },
    "dux_invoice_error": {
      "type": "text"
    },
    "dux_invoice_created_at": {
      "type": "datetime"
    },
    "dux_invoice_attempts": {
      "type": "integer",
      "default": 0
    }
  }
}
